[
  {
    "id": "r_vH-NyOYAg",
    "slug": "monerokon22-reducing-moneros-friction-points-for-rapid-widespread-adoption",
    "videoId": "r_vH-NyOYAg",
    "url": "https://www.youtube.com/watch?v=r_vH-NyOYAg",
    "publishedAt": "2022-06-22T17:47:41Z",
    "desc": "Monero Konferenco 2022 #MoneroKon2022 Lisbon - Day 1",
    "duration": 861,
    "name": "Reducing Monero's Friction Points for Rapid Widespread Adoption",
    "project": "monerokon",
    "event": "monerokon22",
    "people": [
      "Henry"
    ]
  },
  {
    "id": "g_ehNdMsPIM",
    "slug": "monerokon22-financial-oppression-throughout-history",
    "videoId": "g_ehNdMsPIM",
    "url": "https://www.youtube.com/watch?v=g_ehNdMsPIM",
    "publishedAt": "2022-06-22T19:32:39Z",
    "desc": "Monero Konferenco 2022 #MoneroKon2022 Lisbon - Day 1",
    "duration": 1546,
    "name": "Financial Oppression Throughout History",
    "project": "monerokon",
    "event": "monerokon22",
    "people": [
      "Nathan"
    ]
  },
  {
    "id": "566950WnM1c",
    "slug": "monerokon22-why-we-monerujo",
    "videoId": "566950WnM1c",
    "url": "https://www.youtube.com/watch?v=566950WnM1c",
    "publishedAt": "2022-06-24T09:44:35Z",
    "desc": "Monero Konferenco 2022 #MoneroKon2022 Lisbon - Day 1",
    "duration": 1447,
    "name": "Why we Monerujo?",
    "project": "monerokon",
    "event": "monerokon22",
    "people": [
      "Andrés"
    ]
  },
  {
    "id": "mwWWem67W08",
    "slug": "monerokon22-user-perceived-privacy-in-blockchain",
    "videoId": "mwWWem67W08",
    "url": "https://www.youtube.com/watch?v=mwWWem67W08",
    "publishedAt": "2022-06-24T21:59:41Z",
    "desc": "Monero Konferenco 2022 #MoneroKon2022 Lisbon - Day 1",
    "duration": 1173,
    "name": "User Perceived Privacy in Blockchain",
    "project": "monerokon",
    "event": "monerokon22",
    "people": [
      "Simin Ghesmati"
    ]
  },
  {
    "id": "cMZz2JGdXsU",
    "slug": "monerokon22-risks-and-problems-when-shopping-on-the-internet",
    "videoId": "cMZz2JGdXsU",
    "url": "https://www.youtube.com/watch?v=cMZz2JGdXsU",
    "publishedAt": "2022-06-25T14:26:47Z",
    "desc": "Monero Konferenco 2022 #MoneroKon2022 Lisbon - Day 1\n\nhttps://proxysto.re\nhttps://dys2p.com",
    "duration": 1380,
    "name": "Risks and Problems When Shopping on the Internet",
    "project": "monerokon",
    "event": "monerokon22",
    "people": [
      "b068931cc450442b63f5b3d276ea4297",
      "d2ro"
    ]
  },
  {
    "id": "getCBpyXGmM",
    "slug": "monerokon22-building-web3-with-monero",
    "videoId": "getCBpyXGmM",
    "url": "https://www.youtube.com/watch?v=getCBpyXGmM",
    "publishedAt": "2022-06-26T10:42:04Z",
    "desc": "Monero Konferenco 2022 #MoneroKon2022 Lisbon - Day 1 | Lightning Session 1",
    "duration": 402,
    "name": "Building Web3 with Monero",
    "project": "monerokon",
    "event": "monerokon22",
    "people": [
      "AlexAnarcho"
    ]
  },
  {
    "id": "oxiJ7LBJfG0",
    "slug": "monerokon22-atomic-swaps-present-and-future-of-the-farcaster-protocol",
    "videoId": "oxiJ7LBJfG0",
    "url": "https://www.youtube.com/watch?v=oxiJ7LBJfG0",
    "publishedAt": "2022-06-26T20:37:23Z",
    "desc": "Monero Konferenco 2022 #MoneroKon2022 Lisbon - Day 1 | Lightning Session 1",
    "duration": 369,
    "name": "Atomic Swaps: Present and Future of the Farcaster Protocol",
    "project": "monerokon",
    "event": "monerokon22",
    "people": [
      "TheCharlatan"
    ]
  },
  {
    "id": "LkBvVADqEWI",
    "slug": "monerokon22-fireside-chat-with-director-marc-meillassoux",
    "videoId": "LkBvVADqEWI",
    "url": "https://www.youtube.com/watch?v=LkBvVADqEWI",
    "publishedAt": "2022-06-26T22:00:15Z",
    "desc": "Monero Konferenco 2022 #MoneroKon2022 Lisbon - Day 1",
    "duration": 1106,
    "name": "Fireside chat with Director Marc Meillassoux",
    "project": "monerokon",
    "event": "monerokon22",
    "people": [
      "sethforprivacy"
    ]
  },
  {
    "id": "RSCziwwIvoc",
    "slug": "monerokon22-network-level-anonymity-and-transaction-privacy",
    "videoId": "RSCziwwIvoc",
    "url": "https://www.youtube.com/watch?v=RSCziwwIvoc",
    "publishedAt": "2022-06-27T08:33:52Z",
    "desc": "Monero Konferenco  #MoneroKon2022 Day 1 | Lightning Session 1",
    "duration": 335,
    "name": "Network-level Anonymity and Transaction Privacy",
    "project": "monerokon",
    "event": "monerokon22",
    "people": [
      "max-hampshire"
    ]
  },
  {
    "id": "vm_Kw5m_Osk",
    "slug": "monerokon22-how-and-why",
    "videoId": "vm_Kw5m_Osk",
    "url": "https://www.youtube.com/watch?v=vm_Kw5m_Osk",
    "publishedAt": "2022-06-28T19:14:35Z",
    "desc": "Monero Konferenco #MoneroKon2022 Lisbon - Day 1",
    "duration": 2151,
    "name": " Decentralizing Monero Mining: How and Why",
    "project": "monerokon",
    "event": "monerokon22",
    "people": [
      "Howard Chu (hyc)"
    ]
  },
  {
    "id": "4pj8ws005N4",
    "slug": "monerokon22-make-monero-peer-to-peer-again",
    "videoId": "4pj8ws005N4",
    "url": "https://www.youtube.com/watch?v=4pj8ws005N4",
    "publishedAt": "2022-06-28T21:10:40Z",
    "desc": "How Crypto Dealers will Return Crypto to its Cypherpunk Roots Monero Konferenco #MoneroKon2022 Day 1",
    "duration": 1870,
    "name": "Make Monero Peer to Peer Again!",
    "project": "monerokon",
    "event": "monerokon22",
    "people": [
      "juraj-bednar"
    ]
  },
  {
    "id": "C8qtPl74Uso",
    "slug": "monerokon22-trying-to-de-anonymize-i2p-network-participants",
    "videoId": "C8qtPl74Uso",
    "url": "https://www.youtube.com/watch?v=C8qtPl74Uso",
    "publishedAt": "2022-07-05T15:40:07Z",
    "desc": "https://odysee.com/@diva.exchange:d\nTrying to De-Anonymize I2P Network Participants and its Relation to Crypto Swaps Involving Monero #MoneroKon2022 Monero Konferenco | Day 1",
    "duration": 2126,
    "name": "Trying to De-Anonymize I2P Network Participants",
    "project": "monerokon",
    "event": "monerokon22",
    "people": [
      "Konrad Baechler",
      "Marco Purtschert",
      "Brian Boss"
    ]
  },
  {
    "id": "bZaX1hgv-6Q",
    "slug": "monerokon22-partial-linkable-spontaneous-anonymous-group-plsag",
    "videoId": "bZaX1hgv-6Q",
    "url": "https://www.youtube.com/watch?v=bZaX1hgv-6Q",
    "publishedAt": "2022-07-09T07:10:38Z",
    "desc": "Monero Konferenco #MoneroKon2022 Lisbon | Day 1",
    "duration": 401,
    "name": "Partial Linkable Spontaneous Anonymous Group (PLSAG)",
    "project": "monerokon",
    "event": "monerokon22",
    "people": [
      "Haruto Yamamoto"
    ]
  },
  {
    "id": "fEJpE7LumG8",
    "slug": "monerokon22-seraphis-balance-recovery",
    "videoId": "fEJpE7LumG8",
    "url": "https://www.youtube.com/watch?v=fEJpE7LumG8",
    "publishedAt": "2022-08-25T18:19:55Z",
    "desc": "#MoneroKon2022 Monero Konferenco 2022 Day 2",
    "duration": 4326,
    "name": "Seraphis Balance Recovery",
    "project": "monerokon",
    "event": "monerokon22",
    "people": [
      "koe"
    ]
  },
  {
    "id": "hEhXopfzY10",
    "slug": "monerokon22-darkfi-anonymous-engineering-for-dank-net-markets",
    "videoId": "hEhXopfzY10",
    "url": "https://www.youtube.com/watch?v=hEhXopfzY10",
    "publishedAt": "2022-11-06T15:56:20Z",
    "desc": "#monero #monerokon2022 Monero Konferenco 2022 | Lisbon",
    "duration": 1570,
    "name": "DarkFi: Anonymous Engineering for Dank Net Markets",
    "project": "monerokon",
    "event": "monerokon22",
    "people": [
      "amir-taaki"
    ]
  },
  {
    "id": "xGEBRQU1lzw",
    "slug": "monerokon22-seraphisjamtis-feature-overview-of-the-proposed-upgrade-to-monero",
    "videoId": "xGEBRQU1lzw",
    "url": "https://www.youtube.com/watch?v=xGEBRQU1lzw",
    "publishedAt": "2022-12-01T18:26:20Z",
    "desc": "Seraphis/Jamtis resources: https://github.com/seraphis-migration/strategy/wiki/Seraphis-and-Jamtis-Resources\nSeraphis wallet migration repository: https://github.com/seraphis-migration/wallet3\nIRC/Matrix channel: #no-wallet-left-behind:monero.social\n#monero #monerokon2022 Lisbon #monerokon",
    "duration": 2526,
    "name": "Seraphis/Jamtis: Feature overview of the proposed upgrade to Monero",
    "project": "monerokon",
    "event": "monerokon22",
    "people": [
      "Justin Berman"
    ]
  },
  {
    "id": "9EWsqW0Hy1o",
    "slug": "monerokon22-scalable-digital-currency-for-central-banks",
    "videoId": "9EWsqW0Hy1o",
    "url": "https://www.youtube.com/watch?v=9EWsqW0Hy1o",
    "publishedAt": "2022-12-04T12:02:08Z",
    "desc": "#monero #monerokon #monerokon2022 Lisbon Slides: https://github.com/MoneroKon/meta/raw/main/slides/2022/geoffrey-goodell.pdf",
    "duration": 733,
    "name": "Scalable Digital Currency for Central Banks",
    "project": "monerokon",
    "event": "monerokon22",
    "people": [
      "Geoff Goodell"
    ]
  },
  {
    "id": "9XVMUVvwxUE",
    "slug": "monerokon22-the-need-for-a-layer-two-network-in-monero",
    "videoId": "9XVMUVvwxUE",
    "url": "https://www.youtube.com/watch?v=9XVMUVvwxUE",
    "publishedAt": "2022-12-04T12:19:45Z",
    "desc": "#monero #monerokon #monerokon2022 Lisbon Sides: https://raw.githubusercontent.com/MoneroKon/meta/main/slides/2022/seth.pdf",
    "duration": 1641,
    "name": "The Need for a Layer-two Network in Monero",
    "project": "monerokon",
    "event": "monerokon22",
    "people": [
      "sethforprivacy"
    ]
  },
  {
    "id": "j4lJcK3_ADA",
    "slug": "monerokon22-consequences-of-consequentialism-how-trolley-switchers-derailed-decentralization",
    "videoId": "j4lJcK3_ADA",
    "url": "https://www.youtube.com/watch?v=j4lJcK3_ADA",
    "publishedAt": "2022-12-04T12:41:37Z",
    "desc": "#monero #monerokon #monerokon2022 Lisbon Slides: https://github.com/MoneroKon/meta/raw/main/slides/2022/edwin-den-boer.pdf",
    "duration": 2143,
    "name": "Consequences of Consequentialism: How Trolley Switchers Derailed Decentralization",
    "project": "monerokon",
    "event": "monerokon22",
    "people": [
      "Edwin den Boer"
    ]
  },
  {
    "id": "EcfxkWqXABE",
    "slug": "monerokon22-the-role-of-xmr-in-portuguese-freedom-based-economies",
    "videoId": "EcfxkWqXABE",
    "url": "https://www.youtube.com/watch?v=EcfxkWqXABE",
    "publishedAt": "2022-12-04T13:15:42Z",
    "desc": "#monero #monerokon #monerokon2022 Lisbon",
    "duration": 547,
    "name": "The Role of XMR in Portuguese Freedom-based Economies",
    "project": "monerokon",
    "event": "monerokon22",
    "people": [
      "Mr P",
      "Libre",
      "MRPT and Nala"
    ]
  },
  {
    "id": "cOsQtsrQFh8",
    "slug": "monerokon22-luke-parker-kayabanerve",
    "videoId": "cOsQtsrQFh8",
    "url": "https://www.youtube.com/watch?v=cOsQtsrQFh8",
    "publishedAt": "2023-06-18T20:53:39Z",
    "desc": "MoneroKon 2022",
    "duration": 1136,
    "name": "Why Multisig is Important – And How to do it Right",
    "project": "monerokon",
    "event": "monerokon22",
    "people": [
      "Luke Parker (kayabaNerve)"
    ]
  }
]